kicad_vault/__init__.py
kicad_vault/bom.py
kicad_vault/html_gen.py
kicad_vault/main.py
kicad_vault-0.0.2.dist-info/METADATA
kicad_vault-0.0.2.dist-info/WHEEL
kicad_vault-0.0.2.dist-info/entry_points.txt
kicad_vault-0.0.2.dist-info/RECORD
