Metadata-Version: 2.1
Name: kicad-vault
Version: 0.0.2
Summary: A program to manage kicad BOMs, with vendor integration.
Project-URL: Homepage, https://github.com/o7-machinehum/kicad-vault
Project-URL: Bug Tracker, https://github.com/o7-machinehum/kicad-vault/issues
Author-email: Ryan Walker <walker@interruptlabs.ca>
Classifier: License :: OSI Approved :: MIT License
Classifier: Operating System :: OS Independent
Classifier: Programming Language :: Python :: 3
Requires-Python: >=3.7
Requires-Dist: argparse
Requires-Dist: digikey-api
Requires-Dist: pandas
Requires-Dist: tabulate
Requires-Dist: xmltodict
